app/__init__.py
app/cli.py
app/extraction.py
app/main.py
app/prompting.py
app/signature_generator.py
smartfeed_ai-0.1.0.dist-info/METADATA
smartfeed_ai-0.1.0.dist-info/WHEEL
smartfeed_ai-0.1.0.dist-info/entry_points.txt
smartfeed_ai-0.1.0.dist-info/RECORD
