Metadata-Version: 2.4
Name: smartfeed-ai
Version: 0.1.0
Summary: Smart feed extraction and processing tool with DSPy-powered LLM extraction
Requires-Python: >=3.12
Requires-Dist: chonkie<=1.5.0
Requires-Dist: dspy
Requires-Dist: firecrawl
Requires-Dist: litellm
Requires-Dist: markitdown[docx,pdf,xls,xlsx]
Requires-Dist: numpy<2.0.0
Requires-Dist: openai
Requires-Dist: presidio-analyzer
Requires-Dist: presidio-anonymizer
Requires-Dist: python-dotenv
Requires-Dist: rich
Requires-Dist: spacy>=3.0.0
Requires-Dist: tiktoken
Requires-Dist: trafilatura
Requires-Dist: transformers
